repcal/DecimalTime.py
repcal/RepublicanDate.py
repcal/RepublicanFormatter.py
repcal/__init__.py
repcal/__main__.py
repcal/command_line.py
repcal/format_hints.py
repcal-2.0.0.dist-info/LICENSE
repcal-2.0.0.dist-info/METADATA
repcal-2.0.0.dist-info/WHEEL
repcal-2.0.0.dist-info/entry_points.txt
repcal-2.0.0.dist-info/top_level.txt
repcal-2.0.0.dist-info/RECORD
