Metadata-Version: 2.1
Name: repcal
Version: 2.0.0
Summary: The French Republican calendar and decimal time in Python
Home-page: https://github.com/dekadans/repcal
Author: Tomas Thelander
License: MIT
Classifier: Programming Language :: Python :: 3
Classifier: License :: OSI Approved :: MIT License
Classifier: Operating System :: OS Independent
Requires-Python: >=3.11
License-File: LICENSE
